{
    "Operational": {
        "TEMP_PROBE_ID": "Probe_1",
        "T_PROBE_CH": 8,
        "WPUMP_SLOT": 17,
        "DYEPUMP_SLOT": 18,
        "STIRR_SLOT": 27,
        "SPARE_SLOT": 22,
        "VALVE_SLOTS": [
            24,
            23,
            25
        ],
        "DYE_V_INJ": 0.03,
        "CUVETTE_V": 16,
        "dye_nshots": 1,
        "specAvScans": 6,
        "AUTOSTART": "True",
        "AUTOSTART_MODE": "pump",
        "DURATION": -1,
        "SAMPLING_INTERVAL_MIN": 1,
        "VALID_SAMPLING_INTERVALS": [
            "5",
            "7",
            "10",
            "15",
            "20",
            "30",
            "60"
        ],
        "pumpTime_sec": 60,
        "mixTime": 0,
        "waitTime": 0,
        "ncycles": 4,
        "Spectro_Integration_time": 500.5,
        "Ship_Code": "NB",
        "Valid_ship_codes": [
            "Standalone",
            "NB",
            "FA",
            "TF"
        ],
        "LIGHT_THRESHOLD_STS": 15500,
        "LIGHT_THRESHOLD_FLAME": 60000,
        "Autoadjust_state": "ON",
        "Autoadjust_comment": "Options are ON, OFF, ON_NORED"
    },
    "pH": {
        "LED_SLOTS": [
            12,
            13,
            19,
            16
        ],
        "LED1": 50,
        "LED2": 16,
        "LED3": 60,
        "Default_DYE": "MCP",
        "wl_NIR-": 730,
        "MCP_wl_HI": 434,
        "MCP_wl_I2": 578,
        "TB_wl_HI": 434,
        "TB_wl_I2": 596,
        "LED4": 70,
        "PPHOX_STRING_VERSION": "1",
        "dye_level": 997.8399999999999,
        "dye_level_comment": "one bag 1000 ml, two bags"
    },
    "pCO2": {
        "water_temperature": {
            "WAT_TEMP_CAL": [
                -25.779,
                29.84
            ],
            "WAT_TEMP_CH": 1
        },
        "comment1": "# Water flow calibration coefficients :",
        "WAT_FLOW_CAL": [
            -1.25,
            1.6682
        ],
        "comment2": "# Water pressure calibration coefficients :",
        "WAT_PRES_CAL": [
            -2.5,
            1.75562
        ],
        "comment3": "# Air temperature calibration coefficients :",
        "AIR_TEMP_CAL": [
            80.329,
            17.415
        ],
        "comment4": "# Air pressure calibration coefficients ",
        "AIR_PRES_CAL": [
            781.2273,
            302.2975
        ],
        "comment5": " Water detection voltage threshold :",
        "WAT_DETECT": [
            0,
            1
        ],
        "comment6": " # CO2 molar fraction calibration coefficients :",
        "CO2_FRAC_CAL": [
            -30.439,
            1.4352
        ],
        "QUERY_CO2": "\\x2A\\x4D\\x31\\x0A\\x0D",
        "QUERY_T": "\\x2A\\x41\\x32\\x0A\\x0D",
        "comment7": "# used to be SAVE_PCO2_SEC",
        "pCO2_Sampling_interval": 1,
        "PPCO2_STRING_VERSION": "1"
    },
    "CO3": {
        "WL_1": 234,
        "WL_2": 250,
        "LIGHT_SLOT": 5,
        "comment_co3": "# Pb_perchlor or Pb_chlor",
        "Default_DYE": "Pb_perchlor",
        "PCO3_string_version": "1"
    },
    "TrisBuffer": {
        "Comment": "pH of Tris buffer calibration solution at 25deg",
        "S_tris_buffer": 35,
        "Calibration_threshold": 0.1,
        "Calibration_pump_time": 30,
        "T_tris_buffer": 20
    }
}